myssh-0.1.3.data/scripts/con
myssh-0.1.3.data/scripts/sshentry
ssh_app/__init__.py
ssh_app/alembic.ini
ssh_app/models.py
ssh_app/ssh.db
ssh_app/test.py
ssh_app/migrations/__init__.py
ssh_app/migrations/env.py
ssh_app/migrations/versions/__init__.py
ssh_app/migrations/versions/bfd97209a072_.py
myssh-0.1.3.dist-info/LICENSE.txt
myssh-0.1.3.dist-info/METADATA
myssh-0.1.3.dist-info/WHEEL
myssh-0.1.3.dist-info/top_level.txt
myssh-0.1.3.dist-info/RECORD
