Metadata-Version: 2.1
Name: myssh
Version: 0.1.3
Summary: Useful ssh acess tool.
Home-page: https://github.com/ahmmkh/myssh
Author: Ahmed Khatab
Author-email: ahmmkhh@gmail.com
License: LICENSE.txt
Platform: UNKNOWN
Requires-Dist: alembic (==1.0.11)
Requires-Dist: SQLAlchemy (==1.3.6)
Requires-Dist: argcomplete (==1.10.0)
Requires-Dist: requests (==2.22.0)
